{"MR-mean":19.22405,"asphericity-mean":0.3069455,"balabanj-mean":3.629815,"bertzct-mean":197.7792575,"chi0-mean":8.2320505,"chi0n-mean":7.355462,"chi0v-mean":2.355462,"chi1-mean":4.3540595,"chi1n-mean":3.491591,"chi1v-mean":1.0179845,"chi2n-mean":0.539662,"chi2v-mean":0.539662,"chi3n-mean":0.202254,"chi3v-mean":0.202254,"chi4n-mean":0.0994775,"chi4v-mean":0.0994775,"e-valence-mean":28.0,"eccentricity-mean":0.9222245,"hk-alpha-mean":-0.66,"hk-kappa1-mean":0.6564995,"hk-kappa2-mean":0.992104,"hk-kappa3-mean":0.5272805,"ipc-mean":274.8679305,"isf-mean":0.0131725,"labuteASA-mean":37.252747,"logP-mean":0.60801,"molwt-mean":71.0371135,"molwt-hvy-mean":66.039,"nheavy-mean":5.0,"npr1-mean":0.3751205,"npr2-mean":0.651023,"pbf-mean":0.218088,"pc+-mean":0.50277,"pc--mean":-0.50277,"pmi1-mean":49.751397,"pmi2-mean":98.775046,"pmi3-mean":145.282362,"rbonds-mean":1.0,"rg-mean":1.402841,"rpc+-mean":0.3571,"rpc--mean":0.633741,"spherocity-mean":0.2142025,"tpsa-mean":29.465,"vsa+-mean":18.7573155,"vsa--mean":17.0140255,"vsa-fhyd-mean":0.7516375,"vsa-fneg-mean":0.456839,"vsa-fpneg-mean":0.2483625,"vsa-fpos-mean":0.543161,"vsa-fppos-mean":0.0,"vsa-hyd-mean":28.2256805,"vsa-polar-mean":0.2483625,"vsa-polar+-mean":0.0,"vsa-polar--mean":7.5456605,"MR-min":12.9184,"asphericity-min":0.233128,"balabanj-min":3.468512,"bertzct-min":85.425922,"chi0-min":6.07735,"chi0n-min":4.76371,"chi0v-min":1.76371,"chi1-min":2.943376,"chi1n-min":2.088755,"chi1v-min":0.588755,"chi2n-min":0.25711,"chi2v-min":0.25711,"chi3n-min":0.0,"chi3v-min":0.0,"chi4n-min":0.0,"chi4v-min":0.0,"e-valence-min":24.0,"eccentricity-min":0.886906,"hk-alpha-min":-0.72,"hk-kappa1-min":0.641394,"hk-kappa2-min":0.816667,"hk-kappa3-min":0.432339,"ipc-min":17.086166,"isf-min":0.012624,"labuteASA-min":27.607138,"logP-min":-0.1071,"molwt-min":61.016378,"molwt-hvy-min":58.016,"nheavy-min":4.0,"npr1-min":0.28829,"npr2-min":0.574326,"pbf-min":0.16113,"pc+-min":0.475865,"pc--min":-0.529675,"pmi1-min":41.858899,"pmi2-min":52.041581,"pmi3-min":90.61336,"rbonds-min":1.0,"rg-min":1.229397,"rpc+-min":0.347942,"rpc--min":0.5,"spherocity-min":0.082033,"tpsa-min":15.79,"vsa+-min":16.011414,"vsa--min":10.114318,"vsa-fhyd-min":0.61286,"vsa-fneg-min":0.38714,"vsa-fpneg-min":0.109585,"vsa-fpos-min":0.473462,"vsa-fppos-min":0.0,"vsa-hyd-min":16.011414,"vsa-polar-min":0.109585,"vsa-polar+-min":0.0,"vsa-polar--min":4.977003,"MR-max":25.5297,"asphericity-max":0.380763,"balabanj-max":3.791118,"bertzct-max":310.132593,"chi0-max":10.386751,"chi0n-max":9.947214,"chi0v-max":2.947214,"chi1-max":5.764743,"chi1n-max":4.894427,"chi1v-max":1.447214,"chi2n-max":0.822214,"chi2v-max":0.822214,"chi3n-max":0.404508,"chi3v-max":0.404508,"chi4n-max":0.198955,"chi4v-max":0.198955,"e-valence-max":32.0,"eccentricity-max":0.957543,"hk-alpha-max":-0.6,"hk-kappa1-max":0.671605,"hk-kappa2-max":1.167541,"hk-kappa3-max":0.622222,"ipc-max":532.649695,"isf-max":0.013721,"labuteASA-max":46.898356,"logP-max":1.32312,"molwt-max":81.057849,"molwt-hvy-max":74.062,"nheavy-max":6.0,"npr1-max":0.461951,"npr2-max":0.72772,"pbf-max":0.275046,"pc+-max":0.529675,"pc--max":-0.475865,"pmi1-max":57.643895,"pmi2-max":145.508511,"pmi3-max":199.951364,"rbonds-max":1.0,"rg-max":1.576285,"rpc+-max":0.366258,"rpc--max":0.767482,"spherocity-max":0.346372,"tpsa-max":43.14,"vsa+-max":21.503217,"vsa--max":23.913733,"vsa-fhyd-max":0.890415,"vsa-fneg-max":0.526538,"vsa-fpneg-max":0.38714,"vsa-fpos-max":0.61286,"vsa-fppos-max":0.0,"vsa-hyd-max":40.439947,"vsa-polar-max":0.38714,"vsa-polar+-max":0.0,"vsa-polar--max":10.114318,"MR-diff":12.6113,"asphericity-diff":0.147635,"balabanj-diff":0.322606,"bertzct-diff":224.706671,"chi0-diff":4.309401,"chi0n-diff":5.183504,"chi0v-diff":1.183504,"chi1-diff":2.821367,"chi1n-diff":2.805672,"chi1v-diff":0.858459,"chi2n-diff":0.565104,"chi2v-diff":0.565104,"chi3n-diff":0.404508,"chi3v-diff":0.404508,"chi4n-diff":0.198955,"chi4v-diff":0.198955,"e-valence-diff":8.0,"eccentricity-diff":0.070637,"hk-alpha-diff":0.12,"hk-kappa1-diff":0.030211,"hk-kappa2-diff":0.350874,"hk-kappa3-diff":0.189883,"ipc-diff":515.563529,"isf-diff":0.001097,"labuteASA-diff":19.291218,"logP-diff":1.43022,"molwt-diff":20.041471,"molwt-hvy-diff":16.046,"nheavy-diff":2.0,"npr1-diff":0.173661,"npr2-diff":0.153394,"pbf-diff":0.113916,"pc+-diff":0.05381,"pc--diff":0.05381,"pmi1-diff":15.784996,"pmi2-diff":93.46693,"pmi3-diff":109.338004,"rbonds-diff":0.0,"rg-diff":0.346888,"rpc+-diff":0.018316,"rpc--diff":0.267482,"spherocity-diff":0.264339,"tpsa-diff":27.35,"vsa+-diff":5.491803,"vsa--diff":13.799415,"vsa-fhyd-diff":0.277555,"vsa-fneg-diff":0.139398,"vsa-fpneg-diff":0.277555,"vsa-fpos-diff":0.139398,"vsa-fppos-diff":0.0,"vsa-hyd-diff":24.428533,"vsa-polar-diff":0.277555,"vsa-polar+-diff":0.0,"vsa-polar--diff":5.137315,"hbonds":2.0}